LICENSE
bodhilib/__init__.py
bodhilib/_components.py
bodhilib/_filter.py
bodhilib/_models.py
bodhilib/_plugin.py
bodhilib/_version.py
bodhilib/common/__init__.py
bodhilib/logging/__init__.py
bodhilib/logging/_logging.py
bodhilib-0.1.16.dist-info/LICENSE
bodhilib-0.1.16.dist-info/METADATA
bodhilib-0.1.16.dist-info/WHEEL
bodhilib-0.1.16.dist-info/RECORD
