Metadata-Version: 2.1
Name: bodhilib
Version: 0.1.16
Summary: An Open Source, Plugin Architecture based, Pythonic and Composable LLM Library
License: MIT
Author: Amir Nagri
Author-email: amir.nagri@proton.me
Requires-Python: >=3.8.1,<3.12
Classifier: License :: OSI Approved :: MIT License
Classifier: Programming Language :: Python :: 3
Classifier: Programming Language :: Python :: 3.9
Classifier: Programming Language :: Python :: 3.10
Classifier: Programming Language :: Python :: 3.11
Requires-Dist: pluggy (>=1.2.0,<2.0.0)
Requires-Dist: pydantic (>=2.4.2,<3.0.0)
